wraps_futures/__init__.py
wraps_futures/either.py
wraps_futures/option.py
wraps_futures/py.typed
wraps_futures/result.py
wraps_futures/typing.py
wraps_futures-0.1.0.dist-info/METADATA
wraps_futures-0.1.0.dist-info/WHEEL
wraps_futures-0.1.0.dist-info/licenses/LICENSE
wraps_futures-0.1.0.dist-info/RECORD
