Metadata-Version: 2.3
Name: wraps-futures
Version: 0.1.0
Summary: Futures functionality of wraps.
Project-URL: Homepage, https://github.com/nekitdev/wraps-futures
Project-URL: Chat, https://nekit.dev/chat
Project-URL: Documentation, https://nekitdev.github.io/wraps-futures
Project-URL: Funding, https://nekit.dev/funding
Project-URL: Issues, https://github.com/nekitdev/wraps-futures/issues
Project-URL: Repository, https://github.com/nekitdev/wraps-futures
Author-email: nekitdev <nekit@nekit.dev>
License: MIT License
License-File: LICENSE
Keywords: either,future,option,python,result
Classifier: Development Status :: 4 - Beta
Classifier: Intended Audience :: Developers
Classifier: License :: OSI Approved :: MIT License
Classifier: Operating System :: OS Independent
Classifier: Programming Language :: Python
Classifier: Programming Language :: Python :: 3
Classifier: Programming Language :: Python :: 3.8
Classifier: Programming Language :: Python :: 3.9
Classifier: Programming Language :: Python :: 3.10
Classifier: Programming Language :: Python :: 3.11
Classifier: Programming Language :: Python :: 3.12
Classifier: Topic :: Utilities
Classifier: Typing :: Typed
Requires-Python: >=3.8
Requires-Dist: attrs>=24.2.0
Requires-Dist: funcs>=0.10.1
Requires-Dist: typing-aliases>=1.10.1
Requires-Dist: typing-extensions>=4.12.2
Requires-Dist: wraps-core>=0.2.0
Requires-Dist: wraps-futures-core>=0.1.1
